meshagent/cli/__init__.py
meshagent/cli/agent.py
meshagent/cli/api_keys.py
meshagent/cli/async_typer.py
meshagent/cli/auth.py
meshagent/cli/auth_async.py
meshagent/cli/call.py
meshagent/cli/chatbot.py
meshagent/cli/cli.py
meshagent/cli/cli_mcp.py
meshagent/cli/cli_secrets.py
meshagent/cli/common_options.py
meshagent/cli/containers.py
meshagent/cli/database.py
meshagent/cli/developer.py
meshagent/cli/helper.py
meshagent/cli/helpers.py
meshagent/cli/host.py
meshagent/cli/mailbot.py
meshagent/cli/mailboxes.py
meshagent/cli/meeting_transcriber.py
meshagent/cli/messaging.py
meshagent/cli/multi.py
meshagent/cli/oauth2.py
meshagent/cli/participant_token.py
meshagent/cli/port.py
meshagent/cli/projects.py
meshagent/cli/queue.py
meshagent/cli/room.py
meshagent/cli/room_services.py
meshagent/cli/rooms.py
meshagent/cli/services.py
meshagent/cli/sessions.py
meshagent/cli/storage.py
meshagent/cli/sync.py
meshagent/cli/task_runner.py
meshagent/cli/version.py
meshagent/cli/voicebot.py
meshagent/cli/webhook.py
meshagent/cli/worker.py
meshagent_cli-0.25.1.dist-info/METADATA
meshagent_cli-0.25.1.dist-info/WHEEL
meshagent_cli-0.25.1.dist-info/entry_points.txt
meshagent_cli-0.25.1.dist-info/top_level.txt
meshagent_cli-0.25.1.dist-info/RECORD
