Metadata-Version: 2.4
Name: meshagent-cli
Version: 0.25.1
Summary: CLI for Meshagent
License-Expression: Apache-2.0
Project-URL: Documentation, https://docs.meshagent.com
Project-URL: Website, https://www.meshagent.com
Project-URL: Source, https://www.meshagent.com
Requires-Python: >=3.13
Requires-Dist: typer~=0.21
Requires-Dist: fastmcp~=2.8
Requires-Dist: opentelemetry-distro~=0.54b1
Requires-Dist: opentelemetry-exporter-otlp-proto-http~=1.33
Requires-Dist: art~=6.5
Requires-Dist: pydantic-yaml~=1.5
Requires-Dist: pathspec~=0.12.1
Requires-Dist: rich~=14.3.0
Requires-Dist: prompt-toolkit~=3.0.52
Provides-Extra: all
Requires-Dist: meshagent-agents[all]~=0.25.1; extra == "all"
Requires-Dist: meshagent-api[all]~=0.25.1; extra == "all"
Requires-Dist: meshagent-computers~=0.25.1; extra == "all"
Requires-Dist: meshagent-openai~=0.25.1; extra == "all"
Requires-Dist: meshagent-anthropic~=0.25.1; extra == "all"
Requires-Dist: meshagent-mcp~=0.25.1; extra == "all"
Requires-Dist: meshagent-tools~=0.25.1; extra == "all"
Requires-Dist: supabase-auth~=2.22.3; extra == "all"
Requires-Dist: prompt-toolkit~=3.0.52; extra == "all"
Provides-Extra: mcp-service
Requires-Dist: meshagent-agents[all]~=0.25.1; extra == "mcp-service"
Requires-Dist: meshagent-api~=0.25.1; extra == "mcp-service"
Requires-Dist: meshagent-mcp~=0.25.1; extra == "mcp-service"
Requires-Dist: meshagent-tools~=0.25.1; extra == "mcp-service"
Requires-Dist: supabase-auth~=2.22.3; extra == "mcp-service"
